{
 "id": 106718,
 "node": [
  {
   "id": 106718,
   "name": "アレックスキッドのミラクルワールド",
   "nameCN": "阿历克斯小子奇幻世界大冒险",
   "image": "https://lain.bgm.tv/pic/cover/m/c9/62/106718_TRO55.jpg",
   "date": "1986-11-01",
   "nsfw": false,
   "platform": "",
   "type": 4
  },
  {
   "id": 308490,
   "name": "Alex Kidd in Miracle World DX",
   "image": "https://lain.bgm.tv/pic/cover/m/a9/03/308490_F2wOd.jpg",
   "date": "2021-06-24",
   "nameCN": "",
   "type": 4,
   "nsfw": false,
   "platform": ""
  }
 ],
 "relate": [
  {
   "relate": "不同演绎",
   "src": 106718,
   "dst": 308490
  },
  {
   "relate": "不同演绎",
   "src": 308490,
   "dst": 106718
  }
 ]
}