{
  "id": "286281",
  "node": [
    {
      "id": 286281,
      "name": "先輩、断じて恋では！",
      "nameCN": "前辈，这不叫恋爱",
      "date": "2019-07-16",
      "type": 1,
      "nsfw": false,
      "platform": "漫画"
    },
    {
      "id": 317813,
      "name": "先輩、断じて恋では!Brush up",
      "nameCN": "前辈，这不叫恋爱！Brush up",
      "date": "2020-09-17",
      "type": 1,
      "nsfw": false,
      "platform": "漫画"
    }
  ],
  "relate": [
    {
      "relateString": "续集",
      "src": 286281,
      "dst": 317813
    },
    {
      "relateString": "前传",
      "src": 317813,
      "dst": 286281
    }
  ]
}