{
  "id": "127068",
  "node": [
    {
      "id": 127068,
      "name": "影の館",
      "nameCN": "影之馆",
      "date": "2013-11-27",
      "type": 1,
      "nsfw": false,
      "platform": "小说"
    },
    {
      "id": 215823,
      "name": "暗闇の封印: 邂逅の章",
      "nameCN": "",
      "date": "2016-05-27",
      "type": 1,
      "nsfw": false,
      "platform": "小说"
    },
    {
      "id": 215824,
      "name": "暗闇の封印: -黎明の章-",
      "nameCN": "",
      "date": "2016-06-25",
      "type": 1,
      "nsfw": false,
      "platform": "小说"
    }
  ],
  "relate": [
    {
      "relateString": "续集",
      "src": 127068,
      "dst": 215823
    },
    {
      "relateString": "前传",
      "src": 215823,
      "dst": 127068
    },
    {
      "relateString": "续集",
      "src": 215823,
      "dst": 215824
    },
    {
      "relateString": "前传",
      "src": 215824,
      "dst": 215823
    }
  ]
}