{
 "id": 392332,
 "node": [
  {
   "id": 392332,
   "name": "むこうがわの礼節",
   "nameCN": "",
   "image": "https://lain.bgm.tv/pic/cover/m/c5/30/392332_90hLZ.jpg",
   "date": "2016-07-14",
   "nsfw": false,
   "platform": "全部游戏",
   "type": 4
  },
  {
   "id": 392333,
   "name": "むこうがわの礼節～知ることの礼節～",
   "nameCN": "",
   "image": "https://lain.bgm.tv/pic/cover/m/03/fe/392333_HrrUh.jpg",
   "type": 4,
   "date": "2017-12-22",
   "nsfw": false,
   "platform": "全部游戏"
  }
 ],
 "relate": [
  {
   "relate": "续集",
   "src": 392332,
   "dst": 392333
  },
  {
   "relate": "前传",
   "src": 392333,
   "dst": 392332
  }
 ]
}