{
  "id": "131623",
  "node": [
    {
      "id": 131623,
      "name": "LOVE:QUIZ～恋する乙女のファイナルアンサー～",
      "nameCN": "",
      "date": "2015-12-10",
      "type": 4,
      "nsfw": false,
      "platform": "全部游戏"
    },
    {
      "id": 198163,
      "name": "LOVE：QUIZ◆",
      "nameCN": "",
      "type": 4,
      "nsfw": false,
      "platform": "全部游戏"
    }
  ],
  "relate": [
    {
      "relateString": "不同演绎",
      "src": 131623,
      "dst": 198163
    },
    {
      "relateString": "不同演绎",
      "src": 198163,
      "dst": 131623
    }
  ]
}