{
 "id": "222212",
 "node": [
  {
   "id": 215929,
   "name": "sin 光臨天使エンシェル・レナ ～REINCARNATION～",
   "image": "//lain.bgm.tv/pic/cover/m/4a/10/215929_1u0Ub.jpg"
  },
  {
   "id": 222212,
   "name": "光臨天使エンシェル・レナ",
   "image": "//lain.bgm.tv/pic/cover/m/d1/20/222212_MiHV8.jpg"
  },
  {
   "id": 222239,
   "name": "魔法戦士エクストラステージ ～10th　Anniversary～",
   "nameCN": "",
   "image": "//lain.bgm.tv/pic/cover/m/f0/3b/222239_CTazU.jpg"
  }
 ],
 "relate": [
  {
   "relate": "续集",
   "src": 222212,
   "dst": 215929
  },
  {
   "relate": "主线故事",
   "src": 222239,
   "dst": 222212
  }
 ]
}