{
  "id": 527047,
  "node": [
    {
      "id": 527047,
      "name": "营销号说你喜欢我 第一季",
      "nameCN": "",
      "date": "2020-08-04",
      "type": 6,
      "nsfw": false,
      "platform": "其他"
    },
    {
      "id": 527048,
      "name": "营销号说你喜欢我 第二季",
      "nameCN": "",
      "date": "2021-05-01",
      "type": 6,
      "nsfw": false,
      "platform": "其他"
    },
    {
      "id": 527049,
      "name": "マーケティングで愛を囁く シーズン１",
      "nameCN": "营销号说你喜欢我（日语版）第一季",
      "date": "2020-08-23",
      "type": 6,
      "nsfw": false,
      "platform": "其他"
    },
    {
      "id": 527535,
      "name": "營銷號說你喜歡我 粵語版 第一季",
      "nameCN": "营销号说你喜欢我 粤语版 第一季",
      "date": "2020-09-22",
      "type": 6,
      "nsfw": false,
      "platform": "其他"
    }
  ],
  "relate": [
    {
      "relate": "续集",
      "src": 527047,
      "dst": 527048
    },
    {
      "relate": "不同演绎",
      "src": 527047,
      "dst": 527049
    },
    {
      "relate": "不同演绎",
      "src": 527047,
      "dst": 527535
    },
    {
      "relate": "前传",
      "src": 527048,
      "dst": 527047
    },
    {
      "relate": "不同演绎",
      "src": 527049,
      "dst": 527047
    },
    {
      "relate": "不同演绎",
      "src": 527049,
      "dst": 527535
    },
    {
      "relate": "不同演绎",
      "src": 527535,
      "dst": 527047
    },
    {
      "relate": "不同演绎",
      "src": 527535,
      "dst": 527049
    }
  ]
}