{
  "id": 18708,
  "node": [
    {
      "id": 18708,
      "name": "ファントムブレイカー",
      "nameCN": "幻象破灭者",
      "date": "2011-06-02",
      "type": 4,
      "nsfw": false,
      "platform": "Xbox360"
    },
    {
      "id": 76996,
      "name": "ファントムブレイカー エクストラ",
      "nameCN": "幻象破灭者：扩展版",
      "date": "2013-09-19",
      "type": 4,
      "nsfw": false,
      "platform": "全部游戏"
    },
    {
      "id": 67439,
      "name": "ファントムブレイカー バトルグラウンド",
      "nameCN": "幻象破灭者：战斗乐园",
      "date": "2013-02-27",
      "type": 4,
      "nsfw": false,
      "platform": "全部游戏"
    }
  ],
  "relate": [
    {
      "relate": "续集",
      "src": 18708,
      "dst": 76996
    },
    {
      "relate": "主线故事",
      "src": 67439,
      "dst": 18708
    },
    {
      "relate": "前传",
      "src": 76996,
      "dst": 18708
    }
  ]
}