{
  "id": "18975",
  "node": [
    {
      "id": 18975,
      "name": "牧場物語",
      "nameCN": "牧场物语",
      "date": "1996-08-06",
      "type": 4,
      "nsfw": false,
      "platform": "全部游戏"
    },
    {
      "id": 18976,
      "name": "牧場物語GB",
      "nameCN": "牧场物语GB",
      "date": "1997-12-19",
      "type": 4,
      "nsfw": false,
      "platform": "全部游戏"
    },
    {
      "id": 18978,
      "name": "牧場物語2",
      "nameCN": "牧场物语2",
      "date": "1999-02-05",
      "type": 4,
      "nsfw": false,
      "platform": "全部游戏"
    },
    {
      "id": 86004,
      "name": "牧場物語 しあわせの詩",
      "nameCN": "牧场物语 幸福之诗",
      "date": "2005-03-03",
      "type": 4,
      "nsfw": false,
      "platform": "全部游戏"
    },
    {
      "id": 86005,
      "name": "牧場物語 しあわせの詩 for ワールド",
      "nameCN": "牧场物语 幸福之诗 for world",
      "date": "2005-11-10",
      "type": 4,
      "nsfw": false,
      "platform": "全部游戏"
    },
    {
      "id": 18979,
      "name": "牧場物語GB2",
      "nameCN": "牧场物语GB2",
      "date": "1999-08-06",
      "type": 4,
      "nsfw": false,
      "platform": "全部游戏"
    },
    {
      "id": 18983,
      "name": "牧場物語GB3 ボーイ・ミーツ・ガール",
      "nameCN": "牧场物语GB3－当男孩遇上女孩",
      "date": "2000-09-29",
      "type": 4,
      "nsfw": false,
      "platform": "全部游戏"
    }
  ],
  "relate": [
    {
      "relateString": "相同世界观",
      "src": 18975,
      "dst": 18976
    },
    {
      "relateString": "续集",
      "src": 18975,
      "dst": 18978
    },
    {
      "relateString": "相同世界观",
      "src": 18975,
      "dst": 86004
    },
    {
      "relateString": "相同世界观",
      "src": 18975,
      "dst": 86005
    },
    {
      "relateString": "相同世界观",
      "src": 18976,
      "dst": 18975
    },
    {
      "relateString": "续集",
      "src": 18976,
      "dst": 18979
    },
    {
      "relateString": "前传",
      "src": 18978,
      "dst": 18975
    },
    {
      "relateString": "前传",
      "src": 18979,
      "dst": 18976
    },
    {
      "relateString": "续集",
      "src": 18979,
      "dst": 18983
    },
    {
      "relateString": "前传",
      "src": 18983,
      "dst": 18979
    },
    {
      "relateString": "相同世界观",
      "src": 86004,
      "dst": 18975
    },
    {
      "relateString": "不同演绎",
      "src": 86004,
      "dst": 86005
    },
    {
      "relateString": "相同世界观",
      "src": 86005,
      "dst": 18975
    },
    {
      "relateString": "不同演绎",
      "src": 86005,
      "dst": 86004
    }
  ]
}