{
 "id": "265098",
 "node": [
  {
   "id": 265097,
   "name": "Worlds of Ultima: The Savage Empire",
   "nameCN": "创世纪世界：蛮荒帝国",
   "image": "//lain.bgm.tv/pic/cover/m/d8/29/265097_MmZtt.jpg"
  },
  {
   "id": 265098,
   "name": "Ultima: Worlds of Adventure 2: Martian Dreams",
   "nameCN": "创世纪冒险世界2：火星之旅",
   "image": "//lain.bgm.tv/pic/cover/m/9c/8b/265098_SOCsy.jpg"
  }
 ],
 "relate": [
  {
   "relate": "续集",
   "src": 265097,
   "dst": 265098
  },
  {
   "relate": "前传",
   "src": 265098,
   "dst": 265097
  }
 ]
}