{
  "id": 130098,
  "node": [
    {
      "id": 130098,
      "name": "Moana",
      "nameCN": "海洋奇缘",
      "date": "2016-11-23",
      "type": 2,
      "nsfw": false,
      "platform": "剧场版"
    },
    {
      "id": 479822,
      "name": "Moana 2",
      "nameCN": "海洋奇缘2",
      "date": "2024-11-27",
      "type": 2,
      "nsfw": false,
      "platform": "剧场版"
    }
  ],
  "relate": [
    {
      "relate": "续集",
      "src": 130098,
      "dst": 479822
    },
    {
      "relate": "前传",
      "src": 479822,
      "dst": 130098
    }
  ]
}