{
  "id": 130449,
  "node": [
    {
      "id": 130449,
      "name": "こみっくがーるず",
      "nameCN": "漫画女孩",
      "date": "2015-04-27",
      "type": 1,
      "nsfw": false,
      "platform": "漫画"
    },
    {
      "id": 309314,
      "name": "かおす先生のアトリエ探訪",
      "nameCN": "薰子老师的画室探访",
      "date": "2016-01-19",
      "type": 1,
      "nsfw": false,
      "platform": "漫画"
    }
  ],
  "relate": [
    {
      "relate": "番外篇",
      "src": 130449,
      "dst": 309314
    },
    {
      "relate": "主线故事",
      "src": 309314,
      "dst": 130449
    }
  ]
}