{
  "id": 410918,
  "node": [
    {
      "id": 410918,
      "name": "Death on the Nile",
      "nameCN": "尼罗河上的惨案",
      "type": 6,
      "nsfw": false,
      "platform": "其他"
    },
    {
      "id": 449530,
      "name": "Death on the Nile（2022）",
      "nameCN": "尼罗河上的惨案",
      "date": "2022-02-11",
      "type": 6,
      "nsfw": false,
      "platform": "欧美剧"
    }
  ],
  "relate": [
    {
      "relate": "不同演绎",
      "src": 410918,
      "dst": 449530
    },
    {
      "relate": "不同演绎",
      "src": 449530,
      "dst": 410918
    }
  ]
}