{
  "id": 149200,
  "node": [
    {
      "id": 149200,
      "name": "은밀하게 위대하게",
      "nameCN": "伟大的隐藏者",
      "date": "2011-05-09",
      "type": 1,
      "nsfw": false,
      "platform": "漫画"
    },
    {
      "id": 166339,
      "name": "은밀하게 위대하게 slumber",
      "nameCN": "",
      "date": "2013-05-15",
      "type": 1,
      "nsfw": false,
      "platform": "漫画"
    },
    {
      "id": 333323,
      "name": "은밀하게 위대하게2",
      "nameCN": "隐秘而伟大2",
      "date": "2014-12-20",
      "type": 1,
      "nsfw": false,
      "platform": "漫画"
    }
  ],
  "relate": [
    {
      "relate": "番外篇",
      "src": 149200,
      "dst": 166339
    },
    {
      "relate": "前传",
      "src": 149200,
      "dst": 333323
    },
    {
      "relate": "主线故事",
      "src": 166339,
      "dst": 149200
    },
    {
      "relate": "续集",
      "src": 333323,
      "dst": 149200
    }
  ]
}