{
  "id": 30239,
  "node": [
    {
      "id": 30239,
      "name": "ポヨポヨ観察日記",
      "nameCN": "嘟嘟猫观察日记",
      "type": 1,
      "nsfw": false,
      "platform": "漫画"
    },
    {
      "id": 539725,
      "name": "ポヨポヨ観察日記ぷらす",
      "nameCN": "",
      "date": "2025-02-21",
      "type": 1,
      "nsfw": false,
      "platform": "漫画"
    }
  ],
  "relate": [
    {
      "relate": "续集",
      "src": 30239,
      "dst": 539725
    },
    {
      "relate": "前传",
      "src": 539725,
      "dst": 30239
    }
  ]
}