{
  "id": 20529,
  "node": [
    {
      "id": 20529,
      "name": "RAY THE ANIMATION",
      "nameCN": "怪医美女RAY",
      "date": "2006-04-06",
      "type": 2,
      "nsfw": false,
      "platform": "TV"
    },
    {
      "id": 46036,
      "name": "ブラック・ジャック",
      "nameCN": "怪医黑杰克",
      "date": "2004-10-11",
      "type": 2,
      "nsfw": false,
      "platform": "TV"
    },
    {
      "id": 52787,
      "name": "ブラック・ジャック OVA",
      "nameCN": "怪医黑杰克 OVA",
      "date": "1993-12-21",
      "type": 2,
      "nsfw": false,
      "platform": "OVA"
    },
    {
      "id": 80918,
      "name": "ブラック・ジャック21",
      "nameCN": "怪医黑杰克21",
      "date": "2006-04-10",
      "type": 2,
      "nsfw": false,
      "platform": "TV"
    },
    {
      "id": 74542,
      "name": "ブラック・ジャック 劇場版",
      "nameCN": "怪医黑杰克 剧场版",
      "date": "1996-11-30",
      "type": 2,
      "nsfw": false,
      "platform": "剧场版"
    },
    {
      "id": 120069,
      "name": "ブラック・ジャック ふたりの黒い医者",
      "nameCN": "怪医黑杰克 两位神秘医师",
      "date": "2005-12-17",
      "type": 2,
      "nsfw": false,
      "platform": "剧场版"
    },
    {
      "id": 120070,
      "name": "ブラック・ジャック2時間スペシャル 〜命をめぐる4つの奇跡〜",
      "nameCN": "怪医黑杰克特别篇 4个生命的奇迹",
      "date": "2003-12-22",
      "type": 2,
      "nsfw": false,
      "platform": "TV"
    },
    {
      "id": 227563,
      "name": "ブラック・ジャック 空からきた子ども",
      "nameCN": "怪医黑杰克 从天而降的孩子",
      "date": "2000-03-24",
      "type": 2,
      "nsfw": false,
      "platform": "OVA"
    },
    {
      "id": 120067,
      "name": "ブラック・ジャック OVA FINAL",
      "nameCN": "怪医黑杰克 完结篇",
      "date": "2011-12-16",
      "type": 2,
      "nsfw": false,
      "platform": "OVA"
    },
    {
      "id": 348822,
      "name": "ブラック・ジャック / 平安遷都",
      "nameCN": "怪医黑杰克 / 平安迁都",
      "date": "2000-11-03",
      "type": 2,
      "nsfw": false,
      "platform": "剧场版"
    }
  ],
  "relate": [
    {
      "relate": "相同世界观",
      "src": 20529,
      "dst": 46036
    },
    {
      "relate": "相同世界观",
      "src": 20529,
      "dst": 52787
    },
    {
      "relate": "相同世界观",
      "src": 20529,
      "dst": 80918
    },
    {
      "relate": "相同世界观",
      "src": 46036,
      "dst": 20529
    },
    {
      "relate": "不同演绎",
      "src": 46036,
      "dst": 52787
    },
    {
      "relate": "不同演绎",
      "src": 46036,
      "dst": 74542
    },
    {
      "relate": "续集",
      "src": 46036,
      "dst": 80918
    },
    {
      "relate": "番外篇",
      "src": 46036,
      "dst": 120069
    },
    {
      "relate": "番外篇",
      "src": 46036,
      "dst": 120070
    },
    {
      "relate": "不同演绎",
      "src": 46036,
      "dst": 227563
    },
    {
      "relate": "相同世界观",
      "src": 52787,
      "dst": 20529
    },
    {
      "relate": "不同演绎",
      "src": 52787,
      "dst": 46036
    },
    {
      "relate": "番外篇",
      "src": 52787,
      "dst": 74542
    },
    {
      "relate": "不同演绎",
      "src": 52787,
      "dst": 80918
    },
    {
      "relate": "续集",
      "src": 52787,
      "dst": 120067
    },
    {
      "relate": "不同演绎",
      "src": 52787,
      "dst": 227563
    },
    {
      "relate": "不同演绎",
      "src": 52787,
      "dst": 348822
    },
    {
      "relate": "不同演绎",
      "src": 74542,
      "dst": 46036
    },
    {
      "relate": "主线故事",
      "src": 74542,
      "dst": 52787
    },
    {
      "relate": "不同演绎",
      "src": 74542,
      "dst": 80918
    },
    {
      "relate": "主线故事",
      "src": 74542,
      "dst": 120067
    },
    {
      "relate": "相同世界观",
      "src": 80918,
      "dst": 20529
    },
    {
      "relate": "前传",
      "src": 80918,
      "dst": 46036
    },
    {
      "relate": "不同演绎",
      "src": 80918,
      "dst": 52787
    },
    {
      "relate": "不同演绎",
      "src": 80918,
      "dst": 74542
    },
    {
      "relate": "前传",
      "src": 120067,
      "dst": 52787
    },
    {
      "relate": "主线故事",
      "src": 120069,
      "dst": 46036
    },
    {
      "relate": "主线故事",
      "src": 120070,
      "dst": 46036
    },
    {
      "relate": "不同演绎",
      "src": 227563,
      "dst": 46036
    },
    {
      "relate": "不同演绎",
      "src": 227563,
      "dst": 52787
    },
    {
      "relate": "不同演绎",
      "src": 348822,
      "dst": 52787
    }
  ]
}