{
  "id": 20990,
  "node": [
    {
      "id": 20990,
      "name": "Dance Central",
      "nameCN": "热舞中心",
      "date": "2010-11-04",
      "type": 4,
      "nsfw": false,
      "platform": "全部游戏"
    },
    {
      "id": 25624,
      "name": "Dance Central 2",
      "nameCN": "舞蹈中心2",
      "date": "2011-10-27",
      "type": 4,
      "nsfw": false,
      "platform": "全部游戏"
    }
  ],
  "relate": [
    {
      "relate": "续集",
      "src": 20990,
      "dst": 25624
    },
    {
      "relate": "前传",
      "src": 25624,
      "dst": 20990
    }
  ]
}