{
  "id": "105211",
  "node": [
    {
      "id": 105211,
      "name": "ムーンライトエナジー",
      "nameCN": "月光能量",
      "date": "1992-12-10",
      "type": 4,
      "nsfw": false,
      "platform": "全部游戏"
    },
    {
      "id": 113959,
      "name": "ムーンライトエナジー2",
      "nameCN": "月光能量2",
      "date": "1995-12-01",
      "type": 4,
      "nsfw": false,
      "platform": "全部游戏"
    }
  ],
  "relate": [
    {
      "relateString": "续集",
      "src": 105211,
      "dst": 113959
    },
    {
      "relateString": "前传",
      "src": 113959,
      "dst": 105211
    }
  ]
}