{
 "id": 279338,
 "node": [
  {
   "id": 228412,
   "name": "むこうぶち 高レート裏麻雀列伝",
   "nameCN": "雀傀 高倍率黑暗麻将列传",
   "image": "https://lain.bgm.tv/pic/cover/m/05/7f/228412_CzvTc.jpg",
   "date": "2000-11-01",
   "nsfw": false,
   "platform": "漫画",
   "type": 1
  },
  {
   "id": 279338,
   "name": "むこうぶち外伝 EZAKI",
   "nameCN": "雀傀 江崎个人外传",
   "image": "https://lain.bgm.tv/pic/cover/m/b5/d5/279338_8zr3q.jpg",
   "date": "2011-02-17",
   "type": 1,
   "nsfw": false,
   "platform": "漫画"
  }
 ],
 "relate": [
  {
   "relate": "番外篇",
   "src": 228412,
   "dst": 279338
  },
  {
   "relate": "主线故事",
   "src": 279338,
   "dst": 228412
  }
 ]
}