{
  "id": 293,
  "node": [
    {
      "id": 293,
      "name": "Project IGI: I'm Going In",
      "nameCN": "秘密潜入",
      "date": "2000-12-15",
      "type": 4,
      "nsfw": false,
      "platform": "全部游戏"
    },
    {
      "id": 208343,
      "name": "I.G.I.-2: Covert Strike",
      "nameCN": "秘密潜入2：隐秘行动",
      "date": "2003-03-03",
      "type": 4,
      "nsfw": false,
      "platform": "全部游戏"
    }
  ],
  "relate": [
    {
      "relate": "续集",
      "src": 293,
      "dst": 208343
    },
    {
      "relate": "前传",
      "src": 208343,
      "dst": 293
    }
  ]
}