{
 "id": 125937,
 "node": [
  {
   "id": 125937,
   "name": "Ori and the Blind Forest",
   "nameCN": "精灵与森林",
   "image": "https://lain.bgm.tv/pic/cover/m/a1/25/125937_1Q15q.jpg",
   "date": "2015-03-11",
   "nsfw": false,
   "platform": "全部游戏",
   "type": 4
  },
  {
   "id": 216896,
   "name": "Ori and the Will of the Wisps",
   "nameCN": "精灵与萤火意志",
   "image": "https://lain.bgm.tv/pic/cover/m/01/34/216896_I1nK0.jpg",
   "date": "2020-03-11",
   "type": 4,
   "nsfw": false,
   "platform": "全部游戏"
  }
 ],
 "relate": [
  {
   "relate": "续集",
   "src": 125937,
   "dst": 216896
  },
  {
   "relate": "前传",
   "src": 216896,
   "dst": 125937
  }
 ]
}