{
  "id": 162848,
  "node": [
    {
      "id": 162848,
      "name": "青云志",
      "nameCN": "青云志",
      "date": "2016-07-31",
      "type": 6,
      "nsfw": false,
      "platform": "华语剧"
    },
    {
      "id": 215076,
      "name": "青云志Ⅱ",
      "nameCN": "青云志Ⅱ",
      "date": "2016-12-08",
      "type": 6,
      "nsfw": false,
      "platform": "华语剧"
    }
  ],
  "relate": [
    {
      "relate": "续集",
      "src": 162848,
      "dst": 215076
    },
    {
      "relate": "前传",
      "src": 215076,
      "dst": 162848
    }
  ]
}