{
 "id": 182631,
 "node": [
  {
   "id": 182631,
   "name": "Wynonna Earp",
   "image": "//lain.bgm.tv/pic/cover/m/98/d4/182631_Fgz3G.jpg"
  },
  {
   "id": 315190,
   "name": "Wynonna Earp Season 2",
   "nameCN": "狙魔女杰 第二季",
   "image": "//lain.bgm.tv/pic/cover/m/e1/dd/315190_dgG25.jpg"
  },
  {
   "id": 315191,
   "name": "Wynonna Earp Season 3",
   "nameCN": "狙魔女杰 第三季",
   "image": "//lain.bgm.tv/pic/cover/m/a7/c0/315191_I14U1.jpg"
  },
  {
   "id": 315192,
   "name": "Wynonna Earp Season 4 Part 1",
   "nameCN": "狙魔女杰 第四季 上部",
   "image": "//lain.bgm.tv/pic/cover/m/3e/22/315192_xIFfI.jpg"
  }
 ],
 "relate": [
  {
   "relate": "续集",
   "src": 182631,
   "dst": 315190
  },
  {
   "relate": "前传",
   "src": 315190,
   "dst": 182631
  },
  {
   "relate": "续集",
   "src": 315190,
   "dst": 315191
  },
  {
   "relate": "前传",
   "src": 315191,
   "dst": 315190
  },
  {
   "relate": "前传",
   "src": 315192,
   "dst": 315190
  }
 ]
}