{
  "id": 36879,
  "node": [
    {
      "id": 36879,
      "name": "Happy Endings (Season 2)",
      "nameCN": "幸福终点站 第二季",
      "date": "2011-09-28",
      "type": 6,
      "nsfw": false,
      "platform": "欧美剧"
    },
    {
      "id": 59870,
      "name": "Happy Endings (Season 1)",
      "nameCN": "幸福终点站 第一季",
      "date": "2011-04-13",
      "type": 6,
      "nsfw": false,
      "platform": "欧美剧"
    },
    {
      "id": 59871,
      "name": "Happy Endings (Season 3)",
      "nameCN": "幸福终点站 第三季",
      "date": "2012-10-21",
      "type": 6,
      "nsfw": false,
      "platform": "欧美剧"
    }
  ],
  "relate": [
    {
      "relate": "前传",
      "src": 36879,
      "dst": 59870
    },
    {
      "relate": "续集",
      "src": 36879,
      "dst": 59871
    },
    {
      "relate": "续集",
      "src": 59870,
      "dst": 36879
    },
    {
      "relate": "前传",
      "src": 59871,
      "dst": 36879
    }
  ]
}