{
  "id": 62634,
  "node": [
    {
      "id": 62634,
      "name": "幻獣の星座",
      "nameCN": "幻兽星座",
      "type": 1,
      "nsfw": false,
      "platform": "漫画"
    },
    {
      "id": 146187,
      "name": "幻獣の星座〜ダラシャール編〜",
      "nameCN": "幻兽星座～达拉夏尔篇",
      "date": "2014-07-16",
      "type": 1,
      "nsfw": false,
      "platform": "漫画"
    },
    {
      "id": 151274,
      "name": "幻獣の星座 龍王伝",
      "nameCN": "",
      "date": "2014-08-20",
      "type": 1,
      "nsfw": false,
      "platform": "漫画"
    },
    {
      "id": 265975,
      "name": "幻獣の星座~星獣編~",
      "nameCN": "",
      "date": "2016-04-15",
      "type": 1,
      "nsfw": false,
      "platform": "漫画"
    }
  ],
  "relate": [
    {
      "relate": "续集",
      "src": 62634,
      "dst": 146187
    },
    {
      "relate": "番外篇",
      "src": 62634,
      "dst": 151274
    },
    {
      "relate": "相同世界观",
      "src": 62634,
      "dst": 265975
    },
    {
      "relate": "前传",
      "src": 146187,
      "dst": 62634
    },
    {
      "relate": "相同世界观",
      "src": 146187,
      "dst": 151274
    },
    {
      "relate": "续集",
      "src": 146187,
      "dst": 265975
    },
    {
      "relate": "主线故事",
      "src": 151274,
      "dst": 62634
    },
    {
      "relate": "相同世界观",
      "src": 151274,
      "dst": 146187
    },
    {
      "relate": "相同世界观",
      "src": 151274,
      "dst": 265975
    },
    {
      "relate": "相同世界观",
      "src": 265975,
      "dst": 62634
    },
    {
      "relate": "前传",
      "src": 265975,
      "dst": 146187
    },
    {
      "relate": "相同世界观",
      "src": 265975,
      "dst": 151274
    }
  ]
}