{
  "id": 420663,
  "node": [
    {
      "id": 420663,
      "name": "あなたがしてくれなくても",
      "nameCN": "我们之间没有的",
      "date": "2023-04-13",
      "type": 6,
      "nsfw": false,
      "platform": "日剧"
    },
    {
      "id": 442602,
      "name": "あなたがしてくれなくても 特別編",
      "nameCN": "",
      "date": "2023-06-29",
      "type": 6,
      "nsfw": false,
      "platform": "日剧"
    }
  ],
  "relate": [
    {
      "relate": "续集",
      "src": 420663,
      "dst": 442602
    },
    {
      "relate": "前传",
      "src": 442602,
      "dst": 420663
    }
  ]
}