{
  "id": 497153,
  "node": [
    {
      "id": 497153,
      "name": "CLAMP展公式画集 COLOR KURO",
      "nameCN": "",
      "date": "2024-08-07",
      "type": 1,
      "nsfw": false,
      "platform": "画集"
    },
    {
      "id": 497154,
      "name": "CLAMP展公式画集 COLOR SHIRO",
      "nameCN": "",
      "date": "2024-08-07",
      "type": 1,
      "nsfw": false,
      "platform": "画集"
    }
  ],
  "relate": [
    {
      "relate": "续集",
      "src": 497153,
      "dst": 497154
    },
    {
      "relate": "前传",
      "src": 497154,
      "dst": 497153
    }
  ]
}