{
 "id": 221835,
 "node": [
  {
   "id": 221835,
   "name": "Elisa: The Innkeeper",
   "image": "//lain.bgm.tv/pic/cover/m/ac/f9/221835_FwZzv.jpg"
  },
  {
   "id": 226583,
   "name": "Elisa: Seduce the Innkeeper",
   "nameCN": "",
   "image": "//lain.bgm.tv/pic/cover/m/8f/ac/226583_Y0Hze.jpg"
  },
  {
   "id": 226584,
   "name": "Elisa: The Innkeeper - Prequel",
   "nameCN": "",
   "image": "//lain.bgm.tv/pic/cover/m/51/22/226584_I1z6H.jpg"
  }
 ],
 "relate": [
  {
   "relate": "续集",
   "src": 221835,
   "dst": 226583
  },
  {
   "relate": "前传",
   "src": 221835,
   "dst": 226584
  },
  {
   "relate": "前传",
   "src": 226583,
   "dst": 221835
  },
  {
   "relate": "续集",
   "src": 226584,
   "dst": 221835
  }
 ]
}