{
  "id": "75005",
  "node": [
    {
      "id": 75005,
      "name": "鬼嫁日記",
      "nameCN": "鬼嫁日记",
      "date": "2005-10-11",
      "type": 6,
      "nsfw": false,
      "platform": "日剧"
    },
    {
      "id": 75006,
      "name": "鬼嫁日記 いい湯だな",
      "nameCN": "鬼嫁日记2",
      "date": "2007-04-17",
      "type": 6,
      "nsfw": false,
      "platform": "日剧"
    }
  ],
  "relate": [
    {
      "relateString": "续集",
      "src": 75005,
      "dst": 75006
    },
    {
      "relateString": "前传",
      "src": 75006,
      "dst": 75005
    }
  ]
}