{
  "id": 342971,
  "node": [
    {
      "id": 342971,
      "name": "東京幻想作品集",
      "nameCN": "",
      "date": "2020-05-15",
      "type": 1,
      "nsfw": false,
      "platform": "画集"
    },
    {
      "id": 475378,
      "name": "東京幻想作品集II",
      "nameCN": "",
      "date": "2022-08-03",
      "type": 1,
      "nsfw": false,
      "platform": "画集"
    }
  ],
  "relate": [
    {
      "relate": "续集",
      "src": 342971,
      "dst": 475378
    },
    {
      "relate": "前传",
      "src": 475378,
      "dst": 342971
    }
  ]
}