{
  "id": "78548",
  "node": [
    {
      "id": 78548,
      "name": "夢幻外伝",
      "nameCN": "梦幻外传",
      "type": 1,
      "nsfw": false,
      "platform": "漫画"
    },
    {
      "id": 104534,
      "name": "夢幻紳士 冒険活劇篇",
      "nameCN": "梦幻绅士",
      "date": "1982-08-15",
      "type": 1,
      "nsfw": false,
      "platform": "漫画"
    }
  ],
  "relate": [
    {
      "relateString": "前传",
      "src": 78548,
      "dst": 104534
    },
    {
      "relateString": "续集",
      "src": 104534,
      "dst": 78548
    }
  ]
}