{
  "id": "8371",
  "node": [
    {
      "id": 8371,
      "name": "カイチュー!",
      "nameCN": "皆中！Part1",
      "date": "2010-07-16",
      "type": 2,
      "nsfw": false,
      "platform": "WEB"
    },
    {
      "id": 24651,
      "name": "カイチュー! Part.2",
      "nameCN": "皆中！Part.2",
      "date": "2011-10-23",
      "type": 2,
      "nsfw": false,
      "platform": "WEB"
    }
  ],
  "relate": [
    {
      "relateString": "不同演绎",
      "src": 8371,
      "dst": 24651
    },
    {
      "relateString": "不同演绎",
      "src": 24651,
      "dst": 8371
    }
  ]
}