{
  "id": 8829,
  "node": [
    {
      "id": 8829,
      "name": "P.A.",
      "nameCN": "替身天使",
      "date": "1992-01-25",
      "type": 1,
      "nsfw": false,
      "platform": "漫画"
    },
    {
      "id": 56702,
      "name": "P.A. 特別編",
      "nameCN": "P.A. 替身女孩 特别篇",
      "type": 1,
      "nsfw": false,
      "platform": "漫画"
    },
    {
      "id": 425811,
      "name": "P.As.",
      "nameCN": "",
      "date": "2021-10-15",
      "type": 1,
      "nsfw": false,
      "platform": "漫画"
    }
  ],
  "relate": [
    {
      "relate": "番外篇",
      "src": 8829,
      "dst": 56702
    },
    {
      "relate": "续集",
      "src": 8829,
      "dst": 425811
    },
    {
      "relate": "主线故事",
      "src": 56702,
      "dst": 8829
    },
    {
      "relate": "前传",
      "src": 425811,
      "dst": 8829
    }
  ]
}