{
  "id": 313214,
  "node": [
    {
      "id": 313214,
      "name": "クロの戦記 異世界転移した僕が最強なのはベッドの上だけのようです",
      "nameCN": "库洛诺战记 转移到异世界的我最强好像只有床上功夫",
      "type": 1,
      "nsfw": true,
      "platform": "漫画"
    },
    {
      "id": 445274,
      "name": "クロの戦記II 異世界転移した僕が最強なのはベッドの上だけのようです",
      "nameCN": "克罗洛战记II",
      "date": "2023-07-25",
      "type": 1,
      "nsfw": false,
      "platform": "漫画"
    }
  ],
  "relate": [
    {
      "relate": "续集",
      "src": 313214,
      "dst": 445274
    },
    {
      "relate": "前传",
      "src": 445274,
      "dst": 313214
    }
  ]
}