{
 "id": 223129,
 "node": [
  {
   "id": 223129,
   "name": "邪王追妻",
   "nameCN": "邪王追妻",
   "image": "//lain.bgm.tv/pic/cover/m/0e/43/223129_Dsg0H.jpg",
   "date": "2019-01-24"
  },
  {
   "id": 315263,
   "name": "邪王追妻之一世倾城",
   "image": "//lain.bgm.tv/pic/cover/m/80/71/315263_2Ns0n.jpg",
   "date": "2020-12-11"
  },
  {
   "id": 351122,
   "name": "邪王追妻之神女归来",
   "image": "//lain.bgm.tv/pic/cover/m/c5/86/351122_dSSXS.jpg",
   "date": "2021-09-29"
  }
 ],
 "relate": [
  {
   "relate": "续集",
   "src": 223129,
   "dst": 315263
  },
  {
   "relate": "前传",
   "src": 315263,
   "dst": 223129
  },
  {
   "relate": "续集",
   "src": 315263,
   "dst": 351122
  },
  {
   "relate": "前传",
   "src": 351122,
   "dst": 315263
  }
 ]
}