{
  "id": "87004",
  "node": [
    {
      "id": 87004,
      "name": "ワカコ酒",
      "nameCN": "和歌子酒",
      "date": "2013-05-20",
      "type": 1,
      "nsfw": false,
      "platform": "漫画"
    },
    {
      "id": 312385,
      "name": "大衆酒場ワカオ ワカコ酒別店",
      "nameCN": "",
      "date": "2019-08-20",
      "type": 1,
      "nsfw": false,
      "platform": "漫画"
    }
  ],
  "relate": [
    {
      "relateString": "番外篇",
      "src": 87004,
      "dst": 312385
    },
    {
      "relateString": "主线故事",
      "src": 312385,
      "dst": 87004
    }
  ]
}