{
 "id": 114475,
 "node": [
  {
   "id": 114475,
   "name": "SOUND VOLTEX II -infinite infection-",
   "image": "//lain.bgm.tv/pic/cover/m/ed/f9/114475_49Q9Y.jpg"
  },
  {
   "id": 151290,
   "name": "SOUND VOLTEX Booth",
   "nameCN": "",
   "image": "//lain.bgm.tv/pic/cover/m/be/3f/151290_iCrVF.jpg"
  },
  {
   "id": 165737,
   "name": "SOUND VOLTEX III GRAVITY WARS",
   "image": "//lain.bgm.tv/pic/cover/m/c0/de/165737_8Z2PV.jpg"
  },
  {
   "id": 227366,
   "name": "SOUND VOLTEX IV HEAVENLY HAVEN",
   "nameCN": "",
   "image": "//lain.bgm.tv/pic/cover/m/a8/c0/227366_MEM42.jpg"
  }
 ],
 "relate": [
  {
   "relate": "前传",
   "src": 114475,
   "dst": 151290
  },
  {
   "relate": "续集",
   "src": 114475,
   "dst": 165737
  },
  {
   "relate": "续集",
   "src": 151290,
   "dst": 114475
  },
  {
   "relate": "前传",
   "src": 165737,
   "dst": 114475
  },
  {
   "relate": "续集",
   "src": 165737,
   "dst": 227366
  },
  {
   "relate": "前传",
   "src": 227366,
   "dst": 165737
  }
 ]
}