{
 "id": 336234,
 "node": [
  {
   "id": 336230,
   "name": "Big Mouth Season 1",
   "nameCN": "大嘴巴 第一季",
   "image": "https://lain.bgm.tv/pic/cover/m/c8/e7/336230_11O9M.jpg",
   "type": 2
  },
  {
   "id": 336231,
   "name": "Big Mouth Season 2",
   "nameCN": "大嘴巴 第二季",
   "image": "https://lain.bgm.tv/pic/cover/m/fc/06/336231_w94i4.jpg",
   "date": "2018-10-05",
   "nsfw": false,
   "platform": "TV"
  },
  {
   "id": 336232,
   "name": "Big Mouth Season 3",
   "nameCN": "大嘴巴 第三季",
   "image": "https://lain.bgm.tv/pic/cover/m/03/36/336232_zH878.jpg",
   "type": 2
  },
  {
   "id": 336233,
   "name": "Big Mouth Season 4",
   "nameCN": "大嘴巴 第四季",
   "image": "https://lain.bgm.tv/pic/cover/m/82/25/336233_S7gIp.jpg",
   "type": 2,
   "date": "2020-12-04",
   "nsfw": false,
   "platform": "TV"
  },
  {
   "id": 336234,
   "name": "Big Mouth Season 5",
   "nameCN": "大嘴巴 第五季",
   "image": "https://lain.bgm.tv/pic/cover/m/bf/ca/336234_sT5Bq.jpg",
   "date": "2021-11-05",
   "nsfw": false,
   "platform": "TV",
   "type": 2
  },
  {
   "id": 336235,
   "name": "Big Mouth Season 6",
   "nameCN": "大嘴巴 第六季",
   "image": "",
   "type": 2
  }
 ],
 "relate": [
  {
   "relate": "前传",
   "src": 336231,
   "dst": 336230
  },
  {
   "relate": "续集",
   "src": 336231,
   "dst": 336232
  },
  {
   "relate": "前传",
   "src": 336233,
   "dst": 336232
  },
  {
   "relate": "续集",
   "src": 336233,
   "dst": 336234
  },
  {
   "relate": "前传",
   "src": 336234,
   "dst": 336233
  },
  {
   "relate": "续集",
   "src": 336234,
   "dst": 336235
  }
 ]
}