{
  "id": 568047,
  "node": [
    {
      "id": 568047,
      "name": "金刚葫芦妹",
      "nameCN": "",
      "type": 1,
      "nsfw": false,
      "platform": "漫画"
    },
    {
      "id": 568082,
      "name": "葫芦兄妹",
      "nameCN": "",
      "date": "1997-02-01",
      "type": 1,
      "nsfw": false,
      "platform": "漫画"
    }
  ],
  "relate": [
    {
      "relate": "续集",
      "src": 568047,
      "dst": 568082
    },
    {
      "relate": "前传",
      "src": 568082,
      "dst": 568047
    }
  ]
}