{
  "id": "120367",
  "node": [
    {
      "id": 120367,
      "name": "デート～恋とはどんなものかしら～",
      "nameCN": "约会～恋爱究竟是什么呢～",
      "date": "2015-01-19",
      "type": 6,
      "nsfw": false,
      "platform": "日剧"
    },
    {
      "id": 147620,
      "name": "デート～恋とはどんなものかしら～ 2015夏 秘湯",
      "nameCN": "约会～恋爱究竟是什么呢～ 2015夏 秘密温泉",
      "date": "2015-09-28",
      "type": 6,
      "nsfw": false,
      "platform": "日剧"
    }
  ],
  "relate": [
    {
      "relateString": "番外篇",
      "src": 120367,
      "dst": 147620
    },
    {
      "relateString": "主线故事",
      "src": 147620,
      "dst": 120367
    }
  ]
}