{
  "id": "381176",
  "node": [
    {
      "id": 381176,
      "name": "対魔忍アサギ",
      "nameCN": "对魔忍阿萨姫",
      "date": "2011-10-28",
      "type": 1,
      "nsfw": true,
      "platform": "小说"
    },
    {
      "id": 381177,
      "name": "対魔忍アサギ2",
      "nameCN": "",
      "date": "2012-10-30",
      "type": 1,
      "nsfw": true,
      "platform": "小说"
    },
    {
      "id": 381178,
      "name": "対魔忍アサギ3 上巻 最強の対魔忍～井河アサギ編～",
      "nameCN": "",
      "date": "2013-07-26",
      "type": 1,
      "nsfw": true,
      "platform": "小说"
    },
    {
      "id": 381179,
      "name": "対魔忍アサギ3 下巻 鋼鉄の死神～甲河アスカ編～",
      "nameCN": "",
      "date": "2013-07-26",
      "type": 1,
      "nsfw": true,
      "platform": "小说"
    }
  ],
  "relate": [
    {
      "relateString": "续集",
      "src": 381176,
      "dst": 381177
    },
    {
      "relateString": "续集",
      "src": 381176,
      "dst": 381178
    },
    {
      "relateString": "续集",
      "src": 381176,
      "dst": 381179
    },
    {
      "relateString": "前传",
      "src": 381177,
      "dst": 381176
    },
    {
      "relateString": "续集",
      "src": 381177,
      "dst": 381178
    },
    {
      "relateString": "续集",
      "src": 381177,
      "dst": 381179
    },
    {
      "relateString": "前传",
      "src": 381178,
      "dst": 381176
    },
    {
      "relateString": "前传",
      "src": 381178,
      "dst": 381177
    },
    {
      "relateString": "前传",
      "src": 381179,
      "dst": 381176
    },
    {
      "relateString": "前传",
      "src": 381179,
      "dst": 381177
    }
  ]
}