{
 "id": 301559,
 "node": [
  {
   "id": 245769,
   "name": "たとえばラストダンジョン前の村の少年が序盤の街で暮らすような物語",
   "nameCN": "好比是最终迷宫前的少年到新手村生活一般的故事",
   "image": "//lain.bgm.tv/pic/cover/m/76/d4/245769_TMjDS.jpg",
   "date": "2018-02-13"
  },
  {
   "id": 301559,
   "name": "たとえばラストダンジョン前の村の少年が序盤の街の食堂で働く日常物語",
   "nameCN": "好比是最终迷宫前的少年在新手村的食堂打工",
   "image": "//lain.bgm.tv/pic/cover/m/05/bb/301559_29292.jpg",
   "date": "unknown"
  }
 ],
 "relate": [
  {
   "relate": "番外篇",
   "src": 245769,
   "dst": 301559
  },
  {
   "relate": "主线故事",
   "src": 301559,
   "dst": 245769
  }
 ]
}