{
  "id": "86256",
  "node": [
    {
      "id": 86256,
      "name": "RoboKill",
      "nameCN": "杀戮机器",
      "type": 4,
      "nsfw": false,
      "platform": "全部游戏"
    },
    {
      "id": 86259,
      "name": "RoboKill 2",
      "nameCN": "杀戮机器2",
      "type": 4,
      "nsfw": false,
      "platform": "全部游戏"
    }
  ],
  "relate": [
    {
      "relateString": "续集",
      "src": 86256,
      "dst": 86259
    },
    {
      "relateString": "前传",
      "src": 86259,
      "dst": 86256
    }
  ]
}