{
  "id": 315456,
  "node": [
    {
      "id": 315456,
      "name": "SK∞ エスケーエイト",
      "nameCN": "无限滑板",
      "date": "2021-01-09",
      "type": 2,
      "nsfw": false,
      "platform": "TV"
    },
    {
      "id": 340867,
      "name": "SK∞ エスケーエイト 第2期",
      "nameCN": "无限滑板 第2期",
      "type": 2,
      "nsfw": false,
      "platform": "TV"
    },
    {
      "id": 340869,
      "name": "SK∞ エスケーエイト The Stage",
      "nameCN": "舞台剧 无限滑板",
      "type": 6,
      "nsfw": false,
      "platform": "其他"
    },
    {
      "id": 396229,
      "name": "SK∞ エスケーエイト OVA",
      "nameCN": "无限滑板 OVA",
      "type": 2,
      "nsfw": false,
      "platform": "OVA"
    }
  ],
  "relate": [
    {
      "relate": "续集",
      "src": 315456,
      "dst": 340867
    },
    {
      "relate": "不同演绎",
      "src": 315456,
      "dst": 340869
    },
    {
      "relate": "衍生",
      "src": 315456,
      "dst": 396229
    },
    {
      "relate": "前传",
      "src": 340867,
      "dst": 315456
    },
    {
      "relate": "不同演绎",
      "src": 340869,
      "dst": 315456
    },
    {
      "relate": "主线故事",
      "src": 396229,
      "dst": 315456
    }
  ]
}