{
  "id": "289180",
  "node": [
    {
      "id": 289180,
      "name": "Heels Season 1",
      "nameCN": "反派",
      "date": "2021-08-15",
      "type": 6,
      "nsfw": false,
      "platform": "欧美剧"
    },
    {
      "id": 359910,
      "name": "Heels Season 2",
      "nameCN": "反派 第二季",
      "type": 6,
      "nsfw": false,
      "platform": "欧美剧"
    }
  ],
  "relate": [
    {
      "relateString": "续集",
      "src": 289180,
      "dst": 359910
    },
    {
      "relateString": "前传",
      "src": 359910,
      "dst": 289180
    }
  ]
}