{
  "id": 165417,
  "node": [
    {
      "id": 165417,
      "name": "Oxenfree",
      "nameCN": "奥森弗里",
      "date": "2016-01-15",
      "type": 4,
      "nsfw": false,
      "platform": "全部游戏"
    },
    {
      "id": 351141,
      "name": "OXENFREE II: Lost Signals",
      "nameCN": "奥森弗里2 消失的信号",
      "type": 4,
      "nsfw": false,
      "platform": "全部游戏"
    }
  ],
  "relate": [
    {
      "relate": "续集",
      "src": 165417,
      "dst": 351141
    },
    {
      "relate": "前传",
      "src": 351141,
      "dst": 165417
    }
  ]
}