{
  "id": 267251,
  "node": [
    {
      "id": 267251,
      "name": "L'amica geniale Season 1",
      "nameCN": "我的天才女友 第一季",
      "date": "2018-11-18",
      "type": 6,
      "nsfw": false,
      "platform": "欧美剧"
    },
    {
      "id": 268559,
      "name": "L'amica geniale Season 2",
      "nameCN": "我的天才女友 第二季",
      "date": "2020-02-10",
      "type": 6,
      "nsfw": false,
      "platform": "欧美剧"
    },
    {
      "id": 373558,
      "name": "L'amica geniale Season 3",
      "nameCN": "我的天才女友 第三季",
      "date": "2022-02-06",
      "type": 6,
      "nsfw": false,
      "platform": "欧美剧"
    }
  ],
  "relate": [
    {
      "relate": "续集",
      "src": 267251,
      "dst": 268559
    },
    {
      "relate": "前传",
      "src": 268559,
      "dst": 267251
    },
    {
      "relate": "续集",
      "src": 268559,
      "dst": 373558
    },
    {
      "relate": "前传",
      "src": 373558,
      "dst": 268559
    }
  ]
}