{
 "id": 261806,
 "node": [
  {
   "id": 261806,
   "name": "Hilda Season 1",
   "nameCN": "希尔达 第一季",
   "image": "https://lain.bgm.tv/pic/cover/m/5b/93/261806_avs9A.jpg",
   "date": "2018-09-21",
   "nsfw": false,
   "platform": "WEB",
   "type": 2
  },
  {
   "id": 322518,
   "name": "Hilda Season 2",
   "nameCN": "希尔达 第二季",
   "image": "https://lain.bgm.tv/pic/cover/m/1f/b7/322518_OK07h.jpg",
   "date": "2020-12-14",
   "type": 2,
   "nsfw": false,
   "platform": "WEB"
  },
  {
   "id": 361027,
   "name": "Hilda and the Mountain King",
   "nameCN": "希尔达与山丘之王",
   "image": "https://lain.bgm.tv/pic/cover/m/51/d2/361027_JyN75.jpg",
   "date": "2021-12-30",
   "type": 2,
   "nsfw": false,
   "platform": "剧场版"
  }
 ],
 "relate": [
  {
   "relate": "续集",
   "src": 261806,
   "dst": 322518
  },
  {
   "relate": "前传",
   "src": 322518,
   "dst": 261806
  },
  {
   "relate": "续集",
   "src": 322518,
   "dst": 361027
  },
  {
   "relate": "前传",
   "src": 361027,
   "dst": 322518
  }
 ]
}